buildsnap/__init__.py
buildsnap/cli.py
buildsnap-0.2.0.dist-info/licenses/LICENSE
buildsnap-0.2.0.dist-info/METADATA
buildsnap-0.2.0.dist-info/WHEEL
buildsnap-0.2.0.dist-info/entry_points.txt
buildsnap-0.2.0.dist-info/top_level.txt
buildsnap-0.2.0.dist-info/RECORD
