Metadata-Version: 2.4
Name: buildsnap
Version: 0.2.0
Summary: Snap together Python package builds and init
Author-email: imAnesYT <imanesyt.contact@gmail.com>
License: MIT
Project-URL: Homepage, https://github.com/imAnesYT/buildsnap
Requires-Python: >=3.6
License-File: LICENSE
Dynamic: license-file
